[
  {
    "BV2015":"1",
    "Inscrits":"832.2592524397",
    "Abstentions":"345.7204934635",
    "Votants":"486.5387589762",
    "Blancs":"14.9806665439",
    "Nuls":"19.5580924323",
    "Exprimés":"452",
    "N°Panneau":"1",
    "Nuance":"BC-DVD",
    "Binôme":"M. Xavier BALLENGHIEN Mme Valérie MANISSOL",
    "Voix":"205"
  },
  {
    "BV2015":"2",
    "Inscrits":"694.1631375437",
    "Abstentions":"288.3553673357",
    "Votants":"405.8077702081",
    "Blancs":"12.4949364758",
    "Nuls":"16.3128337323",
    "Exprimés":"377",
    "N°Panneau":"1",
    "Nuance":"BC-DVD",
    "Binôme":"M. Xavier BALLENGHIEN Mme Valérie MANISSOL",
    "Voix":"148"
  },
  {
    "BV2015":"3",
    "Inscrits":"705.2108267354",
    "Abstentions":"292.9445774259",
    "Votants":"412.2662493095",
    "Blancs":"12.6937948812",
    "Nuls":"16.5724544283",
    "Exprimés":"383",
    "N°Panneau":"1",
    "Nuance":"BC-DVD",
    "Binôme":"M. Xavier BALLENGHIEN Mme Valérie MANISSOL",
    "Voix":"164"
  },
  {
    "BV2015":"4",
    "Inscrits":"493.4634505616",
    "Abstentions":"204.9847173633",
    "Votants":"288.4787331983",
    "Blancs":"8.8823421101",
    "Nuls":"11.5963910882",
    "Exprimés":"268",
    "N°Panneau":"1",
    "Nuance":"BC-DVD",
    "Binôme":"M. Xavier BALLENGHIEN Mme Valérie MANISSOL",
    "Voix":"121"
  },
  {
    "BV2015":"1",
    "Inscrits":"832.2592524397",
    "Abstentions":"345.7204934635",
    "Votants":"486.5387589762",
    "Blancs":"14.9806665439",
    "Nuls":"19.5580924323",
    "Exprimés":"452",
    "N°Panneau":"2",
    "Nuance":"BC-FG",
    "Binôme":"M. Joël CANTALOUP Mme Sylvie COLAS",
    "Voix":"80"
  },
  {
    "BV2015":"2",
    "Inscrits":"694.1631375437",
    "Abstentions":"288.3553673357",
    "Votants":"405.8077702081",
    "Blancs":"12.4949364758",
    "Nuls":"16.3128337323",
    "Exprimés":"377",
    "N°Panneau":"2",
    "Nuance":"BC-FG",
    "Binôme":"M. Joël CANTALOUP Mme Sylvie COLAS",
    "Voix":"81"
  },
  {
    "BV2015":"3",
    "Inscrits":"705.2108267354",
    "Abstentions":"292.9445774259",
    "Votants":"412.2662493095",
    "Blancs":"12.6937948812",
    "Nuls":"16.5724544283",
    "Exprimés":"383",
    "N°Panneau":"2",
    "Nuance":"BC-FG",
    "Binôme":"M. Joël CANTALOUP Mme Sylvie COLAS",
    "Voix":"66"
  },
  {
    "BV2015":"4",
    "Inscrits":"493.4634505616",
    "Abstentions":"204.9847173633",
    "Votants":"288.4787331983",
    "Blancs":"8.8823421101",
    "Nuls":"11.5963910882",
    "Exprimés":"268",
    "N°Panneau":"2",
    "Nuance":"BC-FG",
    "Binôme":"M. Joël CANTALOUP Mme Sylvie COLAS",
    "Voix":"47"
  },
  {
    "BV2015":"1",
    "Inscrits":"832.2592524397",
    "Abstentions":"345.7204934635",
    "Votants":"486.5387589762",
    "Blancs":"14.9806665439",
    "Nuls":"19.5580924323",
    "Exprimés":"452",
    "N°Panneau":"3",
    "Nuance":"BC-SOC",
    "Binôme":"M. Georges COURTES Mme Suzanne MACABIAU",
    "Voix":"167"
  },
  {
    "BV2015":"2",
    "Inscrits":"694.1631375437",
    "Abstentions":"288.3553673357",
    "Votants":"405.8077702081",
    "Blancs":"12.4949364758",
    "Nuls":"16.3128337323",
    "Exprimés":"377",
    "N°Panneau":"3",
    "Nuance":"BC-SOC",
    "Binôme":"M. Georges COURTES Mme Suzanne MACABIAU",
    "Voix":"148"
  },
  {
    "BV2015":"3",
    "Inscrits":"705.2108267354",
    "Abstentions":"292.9445774259",
    "Votants":"412.2662493095",
    "Blancs":"12.6937948812",
    "Nuls":"16.5724544283",
    "Exprimés":"383",
    "N°Panneau":"3",
    "Nuance":"BC-SOC",
    "Binôme":"M. Georges COURTES Mme Suzanne MACABIAU",
    "Voix":"153"
  },
  {
    "BV2015":"4",
    "Inscrits":"493.4634505616",
    "Abstentions":"204.9847173633",
    "Votants":"288.4787331983",
    "Blancs":"8.8823421101",
    "Nuls":"11.5963910882",
    "Exprimés":"268",
    "N°Panneau":"3",
    "Nuance":"BC-SOC",
    "Binôme":"M. Georges COURTES Mme Suzanne MACABIAU",
    "Voix":"100"
  }
]
