{"CodMinDpt": "34", "CodDpt3Car": "034", "LibDpt": "HERAULT", "Mentions": {"Inscrits": {"Nombre": "772876"}, "Abstentions": {"Nombre": "352785", "RapportInscrit": "45,65"}, "Votants": {"Nombre": "420091", "RapportInscrit": "54,35"}, "Blancs": {"Nombre": "23554", "RapportInscrit": "3,05", "RapportVotant": "5,61"}, "Nuls": {"Nombre": "10686", "RapportInscrit": "1,38", "RapportVotant": "2,54"}, "Exprimes": {"Nombre": "385851", "RapportInscrit": "49,92", "RapportVotant": "91,85"}}, "Resultats": {"NuancesBin": {"NuanceBin": [{"CodNuaBin": "BC-FG", "LibNuaBin": "Bin\u00f4me du Front de Gauche", "NbVoix": "8801", "RapportExprime": "2,28", "RapportInscrit": "1,14", "NbElus": "2"}, {"CodNuaBin": "BC-SOC", "LibNuaBin": "Bin\u00f4me du Parti Socialiste", "NbVoix": "88023", "RapportExprime": "22,81", "RapportInscrit": "11,39", "NbElus": "20"}, {"CodNuaBin": "BC-UG", "LibNuaBin": "Bin\u00f4me Union de la Gauche", "NbVoix": "5831", "RapportExprime": "1,51", "RapportInscrit": "0,75", "NbElus": "0"}, {"CodNuaBin": "BC-DVG", "LibNuaBin": "Bin\u00f4me Divers gauche", "NbVoix": "61728", "RapportExprime": "16,00", "RapportInscrit": "7,99", "NbElus": "14"}, {"CodNuaBin": "BC-VEC", "LibNuaBin": "Bin\u00f4me d'Europe-Ecologie-Les Verts", "NbVoix": "8585", "RapportExprime": "2,22", "RapportInscrit": "1,11", "NbElus": "0"}, {"CodNuaBin": "BC-UMP", "LibNuaBin": "Bin\u00f4me Union pour un Mouvement Populaire", "NbVoix": "42281", "RapportExprime": "10,96", "RapportInscrit": "5,47", "NbElus": "6"}, {"CodNuaBin": "BC-UD", "LibNuaBin": "Bin\u00f4me Union de la Droite", "NbVoix": "30249", "RapportExprime": "7,84", "RapportInscrit": "3,91", "NbElus": "2"}, {"CodNuaBin": "BC-FN", "LibNuaBin": "Bin\u00f4me Front National", "NbVoix": "140353", "RapportExprime": "36,37", "RapportInscrit": "18,16", "NbElus": "6"}]}}}